yelpdataset2sql/datasetparser.py
yelpdataset2sql-0.0.4.dist-info/LICENSE
yelpdataset2sql-0.0.4.dist-info/METADATA
yelpdataset2sql-0.0.4.dist-info/WHEEL
yelpdataset2sql-0.0.4.dist-info/entry_points.txt
yelpdataset2sql-0.0.4.dist-info/top_level.txt
yelpdataset2sql-0.0.4.dist-info/RECORD
