Metadata-Version: 2.1
Name: yelpdataset2sql
Version: 0.0.4
Summary: UNKNOWN
Home-page: UNKNOWN
License: UNKNOWN
Platform: UNKNOWN
Requires-Python: >=3.6
License-File: LICENSE
Requires-Dist: argparse (~=1.4.0)
